rest_pandas/__init__.py
rest_pandas/renderers.py
rest_pandas/serializers.py
rest_pandas/test.py
rest_pandas/views.py
rest_pandas/mustache/rest_pandas.html
rest_pandas-1.1.0.dist-info/LICENSE
rest_pandas-1.1.0.dist-info/METADATA
rest_pandas-1.1.0.dist-info/WHEEL
rest_pandas-1.1.0.dist-info/top_level.txt
rest_pandas-1.1.0.dist-info/RECORD
